sqema/.DS_Store
sqema/SharkBay16S_EG_1.csv
sqema/SharkBay16S_HP_1.csv
sqema/__init__.py
sqema/sqema.py
sqema/sqema_manual_v0.6.pdf
sqema/sqematest_1.csv
sqema-0.6.dist-info/licenses/LICENSE
sqema-0.6.dist-info/WHEEL
sqema-0.6.dist-info/METADATA
sqema-0.6.dist-info/RECORD
